alsh_module.py
alsh_module-0.1.0.dist-info/METADATA
alsh_module-0.1.0.dist-info/WHEEL
alsh_module-0.1.0.dist-info/top_level.txt
alsh_module-0.1.0.dist-info/RECORD
