Metadata-Version: 2.4
Name: alsh_module
Version: 0.1.0
Summary: Example single-file Python module
Author: AlSh
